gennet/__init__.py
gennet/cli.py
gennet/utils/Convert.py
gennet/utils/Convert_topology_npz.py
gennet/utils/Create_network.py
gennet/utils/Create_plots.py
gennet/utils/Dataloader.py
gennet/utils/Interpret.py
gennet/utils/LocallyDirected1D.py
gennet/utils/LocallyDirected1D_scatter.py
gennet/utils/LocallyDirectedConnected.py
gennet/utils/Normalization.py
gennet/utils/Topology.py
gennet/utils/Train_network.py
gennet/utils/Utility_functions.py
gennet/utils/__init__.py
gennet/utils/hase/__init__.py
gennet/utils/hase/config.py
gennet/utils/hase/hase.py
gennet/utils/hase/setup.py
gennet/utils/hase/hase/__init__.py
gennet/utils/hase/hdgwas/__init__.py
gennet/utils/hase/hdgwas/converter.py
gennet/utils/hase/hdgwas/data.py
gennet/utils/hase/hdgwas/fake.py
gennet/utils/hase/hdgwas/hash.py
gennet/utils/hase/hdgwas/hdregression.py
gennet/utils/hase/hdgwas/pard.py
gennet/utils/hase/hdgwas/protocol.py
gennet/utils/hase/hdgwas/regression.py
gennet/utils/hase/hdgwas/tools.py
gennet/utils/hase/tools/VCF2hdf5.py
gennet/utils/hase/tools/__init__.py
gennet/utils/hase/tools/addProbesInfo.py
gennet/utils/hase/tools/analyzer.py
gennet/utils/hase/tools/fix_pheno_id.py
gennet/utils/hase/tools/generator.py
gennet/utils/hase/tools/make_hase_phen.py
gennet/utils/hase/tools/mapper.py
gennet/utils/hase/tools/merge_genotype.py
gennet/utils/hase/tools/minimac2hdf5.py
gennet/utils/hase/tools/rm_subj.py
gennet/utils/hase/tools/tools.py
interpretation/DFIM.py
interpretation/Epistasis_AUC.py
interpretation/NID.py
interpretation/RLIPP.py
interpretation/RLIPP2.py
interpretation/RLIPP_novel_v2.py
interpretation/__init__.py
interpretation/weight_importance.py
gennet_forked-2.0.0.5.dist-info/LICENSE
gennet_forked-2.0.0.5.dist-info/METADATA
gennet_forked-2.0.0.5.dist-info/WHEEL
gennet_forked-2.0.0.5.dist-info/entry_points.txt
gennet_forked-2.0.0.5.dist-info/top_level.txt
gennet_forked-2.0.0.5.dist-info/RECORD
