Metadata-Version: 2.1
Name: gennet-forked
Version: 2.0.0.5
Summary: Framework for Interpretable Neural Networks
Home-page: https://github.com/ArnovanHilten/GenNet
Author: Arno van Hilten
Author-email: arnovanhilten@gmail.com
Requires-Python: >=3.8
License-File: LICENSE
Requires-Dist: h5py >=2.10.0
Requires-Dist: joblib >=0.16.0
Requires-Dist: Markdown >=3.2.1
Requires-Dist: matplotlib >=3.3.2
Requires-Dist: jupyter >=1.0.0
Requires-Dist: numpy
Requires-Dist: pandas >=0.25.3
Requires-Dist: Pillow >=7.2.0
Requires-Dist: plotly >=4.12.0
Requires-Dist: pyparsing >=2.4.7
Requires-Dist: scikit-learn >=0.23.2
Requires-Dist: scipy >=1.4.1
Requires-Dist: seaborn >=0.10.1
Requires-Dist: tables >=3.6.1
Requires-Dist: tqdm >=4.49.0
Requires-Dist: zipp >=3.1.0
Requires-Dist: pytest >=6.2.5
Requires-Dist: protobuf
Requires-Dist: statsmodels
Requires-Dist: shap
Requires-Dist: path-explain
Requires-Dist: psutil
Requires-Dist: kaleido
Requires-Dist: tensorflow <=2.15.1,>=2.13
Requires-Dist: bitarray
Requires-Dist: tensorflow-metal ==1.1.0 ; sys_platform == "darwin"
